## 泛型原理
泛型是JDK的一种语法糖，在JVM层面是没有泛型的。
所以其实就是在编译期间，将泛型转为了实际使用的类，并且也会做类型检查，如果类型不符合要求，则会编译报错

```java
  public static void main(java.lang.String[]);
    descriptor: ([Ljava/lang/String;)V
    flags: ACC_PUBLIC, ACC_STATIC
    Code:
      stack=3, locals=2, args_size=1
         0: new           #3                  // class com/roc/java/common/Generic
         3: dup
         4: ldc           #4                  // String generic paradigm
         6: invokespecial #5                  // Method "<init>":(Ljava/lang/Object;)V
         9: astore_1
        10: getstatic     #6                  // Field java/lang/System.out:Ljava/io/PrintStream;
        13: aload_1
        //getObject时，会有checkcast，将泛型转为String
        14: invokespecial #7                  // Method getObject:()Ljava/lang/Object;
        17: checkcast     #8                  // class java/lang/String
        20: invokevirtual #9                  // Method java/lang/String.toString:()Ljava/lang/String;
        23: invokevirtual #10                 // Method java/io/PrintStream.println:(Ljava/lang/String;)V
        26: return

```